unsplash/__init__.py
unsplash/_client_base.py
unsplash/client.py
unsplash/errors.py
unsplash/models/__init__.py
unsplash/models/_base.py
unsplash/models/collection.py
unsplash/models/photo.py
unsplash/models/search.py
unsplash/models/user.py
unsplash/resources/__init__.py
unsplash/resources/collections.py
unsplash/resources/photos.py
unsplash/resources/search.py
unsplash/resources/users.py
unsplash_pydantic-0.2.1.dist-info/METADATA
unsplash_pydantic-0.2.1.dist-info/WHEEL
unsplash_pydantic-0.2.1.dist-info/licenses/LICENSE
unsplash_pydantic-0.2.1.dist-info/RECORD
