Metadata-Version: 2.4
Name: unsplash-pydantic
Version: 0.2.1
Summary: A modern, Async-ready Unsplash Python API client with Pydantic
License: MIT
License-File: LICENSE
Keywords: unsplash,api,pydantic,photos,images,sdk,async,httpx
Author: Shih-Wei Chris Lo
Author-email: shihwei@gmail.com
Requires-Python: >=3.9,<4.0
Classifier: Development Status :: 4 - Beta
Classifier: Framework :: Pydantic
Classifier: Framework :: Pydantic :: 2
Classifier: Intended Audience :: Developers
Classifier: License :: OSI Approved :: MIT License
Classifier: Operating System :: OS Independent
Classifier: Programming Language :: Python :: 3
Classifier: Programming Language :: Python :: 3.9
Classifier: Programming Language :: Python :: 3.10
Classifier: Programming Language :: Python :: 3.11
Classifier: Programming Language :: Python :: 3.12
Classifier: Programming Language :: Python :: 3.13
Classifier: Programming Language :: Python :: 3.14
Classifier: Topic :: Internet :: WWW/HTTP
Classifier: Topic :: Multimedia :: Graphics
Classifier: Topic :: Software Development :: Libraries :: Python Modules
Classifier: Typing :: Typed
Requires-Dist: httpx (>=0.28.1,<0.29.0)
Requires-Dist: pydantic (>=2.6.0,<3.0.0)
Requires-Dist: typing-extensions (>=4.7.0,<5.0.0) ; python_version < "3.11"
Project-URL: Documentation, https://github.com/shihweilo/unsplash-pydantic#readme
Project-URL: Homepage, https://github.com/shihweilo/unsplash-pydantic
Project-URL: Repository, https://github.com/shihweilo/unsplash-pydantic
